PyAXBPS/__init__.py
PyAXBPS/autoqc.py
PyAXBPS/fileinteraction.py
PyAXBPS/AXBTProcessor/AXBTprocessor.py
PyAXBPS/AXCPProcessor/AXCPprocessor.py
PyAXBPS/AXCPProcessor/WMM.COF
PyAXBPS/AXCPProcessor/_AXCP_convert_fxns.py
PyAXBPS/AXCPProcessor/_AXCP_decode_fxns.py
PyAXBPS/AXCPProcessor/geomag_axbps.py
PyAXBPS/AXCTDProcessor/AXCTDprocessor.py
PyAXBPS/AXCTDProcessor/demodulate.py
PyAXBPS/AXCTDProcessor/parse.py
PyAXBPS/AXCTDProcessor/temp_LUT.txt
PyAXBPS/cmd_line/process_AXBT.py
PyAXBPS/cmd_line/process_AXCP.py
PyAXBPS/cmd_line/process_AXCTD.py
PyAXBPS-1.1.0.dist-info/METADATA
PyAXBPS-1.1.0.dist-info/WHEEL
PyAXBPS-1.1.0.dist-info/top_level.txt
PyAXBPS-1.1.0.dist-info/RECORD
