Metadata-Version: 2.1
Name: PyAXBPS
Version: 1.1.0
Summary: A python package to process AXBT, AXCTD, and AXCP profiles via command line or python scripts
Author-email: Casey Densmore <cdensmore101@gmail.com>
Project-URL: Homepage, https://github.com/cdens/PyAXBPS
Project-URL: Bug Tracker, https://github.com/cdens/PyAXBPS/issues
Classifier: Programming Language :: Python :: 3
Classifier: License :: OSI Approved :: GNU General Public License v3 or later (GPLv3+)
Classifier: Operating System :: OS Independent
Requires-Python: >=3.7
